mcpcn_server_file_finder/__init__.py
mcpcn_server_file_finder/__main__.py
mcpcn_server_file_finder/everything_sdk.py
mcpcn_server_file_finder/platform_search.py
mcpcn_server_file_finder/search_interface.py
mcpcn_server_file_finder/server.py
mcpcn_server_file_finder-0.2.1.dist-info/METADATA
mcpcn_server_file_finder-0.2.1.dist-info/WHEEL
mcpcn_server_file_finder-0.2.1.dist-info/entry_points.txt
mcpcn_server_file_finder-0.2.1.dist-info/licenses/LICENSE
mcpcn_server_file_finder-0.2.1.dist-info/RECORD
